checker/__init__.py
harken_checker-0.1.0.dist-info/METADATA
harken_checker-0.1.0.dist-info/WHEEL
harken_checker-0.1.0.dist-info/RECORD
